haidetector/__init__.py
haidetector/version.py
haidetector/examples/01.hand_landmarks.py
haidetector/examples/02.hand_fingerup.py
haidetector/examples/03.hand_distance.py
haidetector/examples/04.face_landmarks.py
haidetector/examples/05.pose_landmarks.py
haidetector/examples/06.pose_calc.py
haidetector/examples/07.tm_image.py
haidetector/ext/__init__.py
haidetector/ext/face_detector/__init__.py
haidetector/ext/face_detector/face_detector.py
haidetector/ext/hands_detector/__init__.py
haidetector/ext/hands_detector/hands_detector.py
haidetector/ext/pose_detector/__init__.py
haidetector/ext/pose_detector/pose_detector.py
haidetector/ext/tmimage/__init__.py
haidetector/ext/tmimage/tm_imageproject.py
haidetector-0.5.dist-info/METADATA
haidetector-0.5.dist-info/WHEEL
haidetector-0.5.dist-info/top_level.txt
haidetector-0.5.dist-info/RECORD
