Metadata-Version: 2.1
Name: haidetector
Version: 0.5
Summary: A Python Library For HelloAI
Home-page: http://www.moyalab.com
Download-URL: https://www.moyalab.com
Author: devdio
Author-email: iammoyalab@gmail.com
License: GNU GPLv3
Keywords: HelloAI,AI,Robot,CV
Classifier: Intended Audience :: Education
Classifier: Operating System :: Microsoft :: Windows
Classifier: Programming Language :: Python :: 3.8
Classifier: Topic :: Education
Requires-Python: >=3.8
Requires-Dist: helloai (>=1.9)
